freshdesk_mcp/__init__.py
freshdesk_mcp/server.py
freshdesk_mcp_support-1.1.0.dist-info/METADATA
freshdesk_mcp_support-1.1.0.dist-info/WHEEL
freshdesk_mcp_support-1.1.0.dist-info/entry_points.txt
freshdesk_mcp_support-1.1.0.dist-info/RECORD
