Metadata-Version: 2.4
Name: freshdesk-mcp-support
Version: 1.1.0
Summary: An MCP server for Freshdesk
Author-email: Kalidass Mani <kalidass.mani@freshworks.com>
Requires-Python: >=3.10
Requires-Dist: aiohttp>=3.8.0
Requires-Dist: build>=1.2.2.post1
Requires-Dist: httpx==0.28.1
Requires-Dist: mcp[cli]>=1.3.0
Requires-Dist: pydantic>=2.10.6
